skele/__init__.py
skele/cli.py
skele/commands/__init__.py
skele/commands/base.py
skele/commands/hello.py
skele_test-1.0.0.dist-info/DESCRIPTION.rst
skele_test-1.0.0.dist-info/METADATA
skele_test-1.0.0.dist-info/RECORD
skele_test-1.0.0.dist-info/WHEEL
skele_test-1.0.0.dist-info/entry_points.txt
skele_test-1.0.0.dist-info/metadata.json
skele_test-1.0.0.dist-info/top_level.txt
